{
  "version": "8",
  "dialect": "postgres",
  "id": "e4412c17-c012-498f-b352-f5baac4169bb",
  "prevIds": [
    "058bce23-618d-4bc8-a9d7-2c549daf262c"
  ],
  "ddl": [
    {
      "isRlsEnabled": false,
      "name": "roles",
      "entityType": "tables",
      "schema": "public"
    },
    {
      "isRlsEnabled": false,
      "name": "users",
      "entityType": "tables",
      "schema": "public"
    },
    {
      "type": "integer",
      "typeSchema": null,
      "notNull": true,
      "dimensions": 0,
      "default": null,
      "generated": null,
      "identity": {
        "type": "always",
        "name": "roles_id_seq",
        "increment": "1",
        "startWith": "1",
        "minValue": "1",
        "maxValue": "2147483647",
        "cache": 1,
        "cycle": false
      },
      "name": "id",
      "entityType": "columns",
      "schema": "public",
      "table": "roles"
    },
    {
      "type": "varchar(255)",
      "typeSchema": null,
      "notNull": true,
      "dimensions": 0,
      "default": null,
      "generated": null,
      "identity": null,
      "name": "name",
      "entityType": "columns",
      "schema": "public",
      "table": "roles"
    },
    {
      "type": "timestamp",
      "typeSchema": null,
      "notNull": true,
      "dimensions": 0,
      "default": "now()",
      "generated": null,
      "identity": null,
      "name": "created_at",
      "entityType": "columns",
      "schema": "public",
      "table": "roles"
    },
    {
      "type": "timestamp",
      "typeSchema": null,
      "notNull": true,
      "dimensions": 0,
      "default": "now()",
      "generated": null,
      "identity": null,
      "name": "updated_at",
      "entityType": "columns",
      "schema": "public",
      "table": "roles"
    },
    {
      "type": "integer",
      "typeSchema": null,
      "notNull": true,
      "dimensions": 0,
      "default": null,
      "generated": null,
      "identity": null,
      "name": "createdBy",
      "entityType": "columns",
      "schema": "public",
      "table": "roles"
    },
    {
      "type": "integer",
      "typeSchema": null,
      "notNull": true,
      "dimensions": 0,
      "default": null,
      "generated": null,
      "identity": null,
      "name": "updatedBy",
      "entityType": "columns",
      "schema": "public",
      "table": "roles"
    },
    {
      "type": "boolean",
      "typeSchema": null,
      "notNull": true,
      "dimensions": 0,
      "default": "true",
      "generated": null,
      "identity": null,
      "name": "isActive",
      "entityType": "columns",
      "schema": "public",
      "table": "roles"
    },
    {
      "type": "integer",
      "typeSchema": null,
      "notNull": true,
      "dimensions": 0,
      "default": null,
      "generated": null,
      "identity": {
        "type": "always",
        "name": "users_id_seq",
        "increment": "1",
        "startWith": "1",
        "minValue": "1",
        "maxValue": "2147483647",
        "cache": 1,
        "cycle": false
      },
      "name": "id",
      "entityType": "columns",
      "schema": "public",
      "table": "users"
    },
    {
      "type": "varchar(255)",
      "typeSchema": null,
      "notNull": true,
      "dimensions": 0,
      "default": null,
      "generated": null,
      "identity": null,
      "name": "name",
      "entityType": "columns",
      "schema": "public",
      "table": "users"
    },
    {
      "type": "varchar(255)",
      "typeSchema": null,
      "notNull": true,
      "dimensions": 0,
      "default": null,
      "generated": null,
      "identity": null,
      "name": "email",
      "entityType": "columns",
      "schema": "public",
      "table": "users"
    },
    {
      "type": "varchar(255)",
      "typeSchema": null,
      "notNull": true,
      "dimensions": 0,
      "default": null,
      "generated": null,
      "identity": null,
      "name": "password",
      "entityType": "columns",
      "schema": "public",
      "table": "users"
    },
    {
      "type": "varchar(50)",
      "typeSchema": null,
      "notNull": true,
      "dimensions": 0,
      "default": "'employee'",
      "generated": null,
      "identity": null,
      "name": "role",
      "entityType": "columns",
      "schema": "public",
      "table": "users"
    },
    {
      "type": "varchar(255)",
      "typeSchema": null,
      "notNull": false,
      "dimensions": 0,
      "default": null,
      "generated": null,
      "identity": null,
      "name": "avatar",
      "entityType": "columns",
      "schema": "public",
      "table": "users"
    },
    {
      "type": "timestamp",
      "typeSchema": null,
      "notNull": true,
      "dimensions": 0,
      "default": "now()",
      "generated": null,
      "identity": null,
      "name": "created_at",
      "entityType": "columns",
      "schema": "public",
      "table": "users"
    },
    {
      "nameExplicit": false,
      "columns": [
        "createdBy"
      ],
      "schemaTo": "public",
      "tableTo": "users",
      "columnsTo": [
        "id"
      ],
      "onUpdate": "NO ACTION",
      "onDelete": "NO ACTION",
      "name": "roles_createdBy_users_id_fkey",
      "entityType": "fks",
      "schema": "public",
      "table": "roles"
    },
    {
      "nameExplicit": false,
      "columns": [
        "updatedBy"
      ],
      "schemaTo": "public",
      "tableTo": "users",
      "columnsTo": [
        "id"
      ],
      "onUpdate": "NO ACTION",
      "onDelete": "NO ACTION",
      "name": "roles_updatedBy_users_id_fkey",
      "entityType": "fks",
      "schema": "public",
      "table": "roles"
    },
    {
      "columns": [
        "id"
      ],
      "nameExplicit": false,
      "name": "roles_pkey",
      "schema": "public",
      "table": "roles",
      "entityType": "pks"
    },
    {
      "columns": [
        "id"
      ],
      "nameExplicit": false,
      "name": "users_pkey",
      "schema": "public",
      "table": "users",
      "entityType": "pks"
    },
    {
      "nameExplicit": false,
      "columns": [
        "name"
      ],
      "nullsNotDistinct": false,
      "name": "roles_name_key",
      "schema": "public",
      "table": "roles",
      "entityType": "uniques"
    },
    {
      "nameExplicit": false,
      "columns": [
        "email"
      ],
      "nullsNotDistinct": false,
      "name": "users_email_key",
      "schema": "public",
      "table": "users",
      "entityType": "uniques"
    }
  ],
  "renames": []
}